polytruth/__init__.py
polytruth/core.py
polytruth/types.py
polytruth/operator/__init__.py
polytruth/operator/base.py
polytruth/operator/multi_value.py
polytruth/parser/__init__.py
polytruth-0.1.1.dist-info/licenses/LICENSE
polytruth-0.1.1.dist-info/METADATA
polytruth-0.1.1.dist-info/WHEEL
polytruth-0.1.1.dist-info/top_level.txt
polytruth-0.1.1.dist-info/RECORD
