Metadata-Version: 2.4
Name: polytruth
Version: 0.1.1
Summary:  Multi-valued Logic Truth Value Computation Framework
Author-email: Xie Zhongtao <francisol.net@gmail.com>
License-Expression: MIT
Project-URL: Source, https://github.com/francisol/polytruth
Keywords: multi-valued logic,fuzzy logic,truth values,non-classical logic,logical operators
Requires-Python: >=3.8
License-File: LICENSE
Requires-Dist: numpy>=1.20.0
Requires-Dist: ply>=3
Dynamic: license-file
